{".class": "MypyFile", "_fullname": "launch_script", "is_partial_stub_package": false, "is_stub": false, "names": {".class": "SymbolTable", "BASE_COMMAND": {".class": "SymbolTableNode", "kind": "Gdef", "node": {".class": "Var", "flags": [], "fullname": "launch_script.BASE_COMMAND", "name": "BASE_COMMAND", "type": "builtins.str"}}, "PATH": {".class": "SymbolTableNode", "kind": "Gdef", "node": {".class": "Var", "flags": [], "fullname": "launch_script.PATH", "name": "PATH", "type": "builtins.str"}}, "__doc__": {".class": "SymbolTableNode", "kind": "Gdef", "node": {".class": "Var", "flags": ["is_ready"], "fullname": "launch_script.__doc__", "name": "__doc__", "type": "builtins.str"}}, "__file__": {".class": "SymbolTableNode", "kind": "Gdef", "node": {".class": "Var", "flags": ["is_ready"], "fullname": "launch_script.__file__", "name": "__file__", "type": "builtins.str"}}, "__name__": {".class": "SymbolTableNode", "kind": "Gdef", "node": {".class": "Var", "flags": ["is_ready"], "fullname": "launch_script.__name__", "name": "__name__", "type": "builtins.str"}}, "__package__": {".class": "SymbolTableNode", "kind": "Gdef", "node": {".class": "Var", "flags": ["is_ready"], "fullname": "launch_script.__package__", "name": "__package__", "type": "builtins.str"}}, "base_pid": {".class": "SymbolTableNode", "kind": "Gdef", "node": {".class": "Var", "flags": ["is_ready"], "fullname": "launch_script.base_pid", "name": "base_pid", "type": "builtins.int"}}, "base_port": {".class": "SymbolTableNode", "kind": "Gdef", "node": {".class": "Var", "flags": ["is_ready"], "fullname": "launch_script.base_port", "name": "base_port", "type": "builtins.int"}}, "build_command_line": {".class": "SymbolTableNode", "kind": "Gdef", "node": {".class": "FuncDef", "arg_kinds": [0], "arg_names": ["pid"], "flags": [], "fullname": "launch_script.build_command_line", "name": "build_command_line", "type": null}}, "config": {".class": "SymbolTableNode", "kind": "Gdef", "node": {".class": "Var", "flags": [], "fullname": "launch_script.config", "name": "config", "type": "typing.TextIO"}}, "config_path": {".class": "SymbolTableNode", "kind": "Gdef", "node": {".class": "Var", "flags": [], "fullname": "launch_script.config_path", "name": "config_path", "type": "builtins.str"}}, "cur_pid": {".class": "SymbolTableNode", "kind": "Gdef", "node": {".class": "Var", "flags": [], "fullname": "launch_script.cur_pid", "name": "cur_pid", "type": "builtins.int"}}, "get_random_string": {".class": "SymbolTableNode", "kind": "Gdef", "node": {".class": "FuncDef", "arg_kinds": [0], "arg_names": ["length"], "flags": [], "fullname": "launch_script.get_random_string", "name": "get_random_string", "type": null}}, "hosts": {".class": "SymbolTableNode", "kind": "Gdef", "node": {".class": "Var", "flags": [], "fullname": "launch_script.hosts", "name": "hosts", "type": "typing.TextIO"}}, "hosts_path": {".class": "SymbolTableNode", "kind": "Gdef", "node": {".class": "Var", "flags": [], "fullname": "launch_script.hosts_path", "name": "hosts_path", "type": "builtins.str"}}, "i": {".class": "SymbolTableNode", "kind": "Gdef", "node": {".class": "Var", "flags": [], "fullname": "launch_script.i", "name": "i", "type": "builtins.int"}}, "m": {".class": "SymbolTableNode", "kind": "Gdef", "node": {".class": "Var", "flags": [], "fullname": "launch_script.m", "name": "m", "type": "builtins.int"}}, "os": {".class": "SymbolTableNode", "cross_ref": "os", "kind": "Gdef"}, "output_spec_path": {".class": "SymbolTableNode", "kind": "Gdef", "node": {".class": "Var", "flags": ["is_ready"], "fullname": "launch_script.output_spec_path", "name": "output_spec_path", "type": "builtins.str"}}, "process_nb": {".class": "SymbolTableNode", "kind": "Gdef", "node": {".class": "Var", "flags": [], "fullname": "launch_script.process_nb", "name": "process_nb", "type": "builtins.int"}}, "processes": {".class": "SymbolTableNode", "kind": "Gdef", "node": {".class": "Var", "flags": [], "fullname": "launch_script.processes", "name": "processes", "type": {".class": "Instance", "args": [{".class": "Instance", "args": ["builtins.bytes"], "type_ref": "subprocess.Popen"}], "type_ref": "builtins.list"}}}, "random": {".class": "SymbolTableNode", "cross_ref": "random", "kind": "Gdef"}, "shebang": {".class": "SymbolTableNode", "kind": "Gdef", "node": {".class": "Var", "flags": [], "fullname": "launch_script.shebang", "name": "shebang", "type": "builtins.str"}}, "string": {".class": "SymbolTableNode", "cross_ref": "string", "kind": "Gdef"}, "subprocess": {".class": "SymbolTableNode", "cross_ref": "subprocess", "kind": "Gdef"}, "sys": {".class": "SymbolTableNode", "cross_ref": "sys", "kind": "Gdef"}, "time": {".class": "SymbolTableNode", "cross_ref": "time", "kind": "Gdef"}}, "path": "c:\\Users\\antom\\Documents\\LIFE\\EPFL\\MA\\MA1\\DA\\CS451-2021-project\\template_java\\launch_script.py"}